dragocrypt/__init__.py
dragocrypt/dragocrypt.py
dragocrypt-1.7.dist-info/LICENSE
dragocrypt-1.7.dist-info/METADATA
dragocrypt-1.7.dist-info/WHEEL
dragocrypt-1.7.dist-info/top_level.txt
dragocrypt-1.7.dist-info/RECORD
