Metadata-Version: 2.1
Name: dragocrypt
Version: 1.7
Summary: For developers
Home-page: https://github.com/NovaTools4
Author: The Jordan Ghost
Author-email: Novayou0@gmail.com
Project-URL: Bug Tracker, https://github.com/pypa/sampleproject/issues
Keywords: dragocrypt
Classifier: Development Status :: 1 - Planning
Classifier: Intended Audience :: Developers
Classifier: Programming Language :: Python :: 3
Classifier: Operating System :: Unix
Classifier: Operating System :: MacOS :: MacOS X
Classifier: Operating System :: Microsoft :: Windows
License-File: LICENSE
